{
    "Nintendo Wii (EMULADORES)": [
        {
            "nome": "Dolphin v1.1.9.0 - 66.6MB (XBOX DEV MODE)",
            "url": "https://2r70pn-my.sharepoint.com/:u:/g/personal/uploadgames_2r70pn_onmicrosoft_com/Ebqbp4UXitFOqP1BrDcB0OQBFbINP4GyI0f1GTmCpSejDQ?download=1",
            "descricao": "Emulador feito para rodar jogos do Wii no Xbox no modo de desenvolvedor",
            "capa": "https://i4.imageban.ru/out/2025/07/11/ad33ef0232a8396eb63dd49c1f218347.png"
        }
    ]
}
